LICENSE
README.md
setup.cfg
setup.py
blueliv/__init__.py
blueliv/configuration.py
blueliv/core.py
blueliv/crawl.py
blueliv/iocs.py
blueliv/malwares.py
blueliv/sparks.py
blueliv/tags.py
blueliv/users.py
blueliv_api.egg-info/PKG-INFO
blueliv_api.egg-info/SOURCES.txt
blueliv_api.egg-info/dependency_links.txt
blueliv_api.egg-info/requires.txt
blueliv_api.egg-info/top_level.txt