Metadata-Version: 2.1
Name: blueliv-api
Version: 1.0.4
Summary: Blueliv's API encapsulation
Home-page: https://github.com/patowc/blueliv
Author: Román Ramírez
Author-email: rramirez@rootedcon.com
License: MIT
Platform: UNKNOWN
Classifier: Programming Language :: Python :: 3
Classifier: License :: OSI Approved :: MIT License
Classifier: Operating System :: OS Independent
Requires-Python: >=3.6
